pytiva/__init__.py
pytiva/requirements.txt
pytiva/activity/ActivityDataSet.py
pytiva/activity/__init__.py
pytiva/activity/utils.py
pytiva/anesthesia/AnesthesiaCaseDataSet.py
pytiva/anesthesia/AnesthesiaCaseEventsDataSet.py
pytiva/anesthesia/AnesthesiaCaseMedicationsDataSet.py
pytiva/anesthesia/AnesthesiaCaseStaffingDataSet.py
pytiva/anesthesia/AnesthesiaDataSet.py
pytiva/anesthesia/AnesthesiaStudy.py
pytiva/anesthesia/EventActivityDefinition.py
pytiva/anesthesia/__init__.py
pytiva/anesthesia/utils.py
pytiva/dataset/DataSet.py
pytiva/dataset/TimeSeriesDataSet.py
pytiva/dataset/__init__.py
pytiva/staffing/CapacityTSDS.py
pytiva/staffing/ProviderShift.py
pytiva/staffing/ResourceAssignmentDataSet.py
pytiva/staffing/StaffingDataSet.py
pytiva/staffing/__init__.py
pytiva/staffing/utils.py
pytiva/stats/__init__.py
pytiva/stats/utils.py
pytiva/utils/__init__.py
pytiva/utils/utils.py
pytiva/viz/__init__.py
pytiva/viz/gantt.py
pytiva/viz/lineplots.py
pytiva-2023.8.6.1.dist-info/LICENSE
pytiva-2023.8.6.1.dist-info/METADATA
pytiva-2023.8.6.1.dist-info/WHEEL
pytiva-2023.8.6.1.dist-info/top_level.txt
pytiva-2023.8.6.1.dist-info/RECORD
